odoo8_addon_hr_timesheet_invoice_hide_to_invoice_task-8.0.1.0.0.99.dev3-py2.7-nspkg.pth
odoo8_addon_hr_timesheet_invoice_hide_to_invoice_task-8.0.1.0.0.99.dev3.dist-info/DESCRIPTION.rst
odoo8_addon_hr_timesheet_invoice_hide_to_invoice_task-8.0.1.0.0.99.dev3.dist-info/METADATA
odoo8_addon_hr_timesheet_invoice_hide_to_invoice_task-8.0.1.0.0.99.dev3.dist-info/RECORD
odoo8_addon_hr_timesheet_invoice_hide_to_invoice_task-8.0.1.0.0.99.dev3.dist-info/WHEEL
odoo8_addon_hr_timesheet_invoice_hide_to_invoice_task-8.0.1.0.0.99.dev3.dist-info/metadata.json
odoo8_addon_hr_timesheet_invoice_hide_to_invoice_task-8.0.1.0.0.99.dev3.dist-info/namespace_packages.txt
odoo8_addon_hr_timesheet_invoice_hide_to_invoice_task-8.0.1.0.0.99.dev3.dist-info/top_level.txt
odoo_addons/hr_timesheet_invoice_hide_to_invoice_task/README.rst
odoo_addons/hr_timesheet_invoice_hide_to_invoice_task/__init__.py
odoo_addons/hr_timesheet_invoice_hide_to_invoice_task/__openerp__.py
odoo_addons/hr_timesheet_invoice_hide_to_invoice_task/i18n/hr_timesheet_invoice_hide_to_invoice_task.pot
odoo_addons/hr_timesheet_invoice_hide_to_invoice_task/i18n/sl.po
odoo_addons/hr_timesheet_invoice_hide_to_invoice_task/static/description/icon.png
odoo_addons/hr_timesheet_invoice_hide_to_invoice_task/views/hr_timesheet_invoice_hide_to_invoice_task_view.xml
